<?xml version="1.0" encoding="utf-8"?>
<publishData>
  <publishProfile publishUrl="C:\inetpub\Onlinestore" deleteExistingFiles="False" ftpAnonymousLogin="False" ftpPassiveMode="True" msdeploySite="" msdeploySiteID="" msdeployRemoteSitePhysicalPath="" msdeployAllowUntrustedCertificate="False" msdeploySkipExtraFilesOnServer="True" msdeployMarkAsApp="False" profileName="Perfil1" publishMethod="FileSystem" replaceMatchingFiles="True" userName="" savePWD="False" userPWD="" SelectedForPublish="True">
    <file relUrl="StyleDefa.css" publishTime="10/08/2024 01:35:29" />
    <file relUrl="Scripts/jquery-1.4.1.min.js" publishTime="09/27/2024 17:35:04" />
    <file relUrl="Scripts/jquery-1.4.1-vsdoc.js" publishTime="09/27/2024 17:35:04" />
    <file relUrl="login.aspx" publishTime="10/02/2024 01:12:16" />
    <file relUrl="Web.config" publishTime="10/09/2024 00:25:45" />
    <file relUrl="bin/OnlineStore.dll" publishTime="10/09/2024 00:25:45" />
    <file relUrl="Default.aspx" publishTime="10/07/2024 23:09:49" />
    <file relUrl="StyleCss.css" publishTime="10/07/2024 20:04:01" />
    <file relUrl="Scripts/jquery-1.4.1.js" publishTime="09/27/2024 17:35:04" />
    <file relUrl="bin/OnlineStore.pdb" publishTime="10/09/2024 00:25:45" />
  </publishProfile>
</publishData>